NGAsubGMM.py
NGAsubGMMcoeffsKBCG20post.py
NGAsubGMMcoeffsKBCG20post-0.0.7.dist-info/METADATA
NGAsubGMMcoeffsKBCG20post-0.0.7.dist-info/WHEEL
NGAsubGMMcoeffsKBCG20post-0.0.7.dist-info/top_level.txt
NGAsubGMMcoeffsKBCG20post-0.0.7.dist-info/RECORD
