Metadata-Version: 2.1
Name: NGAsubGMMcoeffsKBCG20post
Version: 0.0.7
Summary: A Series of function for Python
Home-page: https://www.silviasbrainery.com/
Author: Silvia Mazzoni
Author-email: silviamazzoni@yahoo.com
License: (c) Silvia Mazzoni
Platform: UNKNOWN
Classifier: Programming Language :: Python :: 2
Classifier: Programming Language :: Python :: 3
Classifier: License :: Other/Proprietary License
Classifier: Operating System :: OS Independent
Requires-Dist: matplotlib
Requires-Dist: numpy
Requires-Dist: pandas
